<?xml version="1.0" encoding="UTF-8" ?>
<!DOCTYPE mapper PUBLIC "-//mybatis.org//DTD Mapper 3.0//EN" "http://mybatis.org/dtd/mybatis-3-mapper.dtd" >
<mapper namespace="com.smedia.sqzserver.dataservice.dao.base.ServersMapper" >
  <resultMap id="BaseResultMap" type="com.smedia.sqzserver.dataservice.model.base.Servers" >
    <!--
      WARNING - @mbggenerated
      This element is automatically generated by MyBatis Generator, do not modify.
      This element was generated on Fri Feb 10 14:15:10 MST 2012.
    -->
    <id column="ServerId" property="serverId" jdbcType="CHAR" />
    <result column="ImageId" property="imageId" jdbcType="VARCHAR" />
    <result column="InstanceId" property="instanceId" jdbcType="VARCHAR" />
    <result column="PublicName" property="publicName" jdbcType="VARCHAR" />
    <result column="PublicIp" property="publicIp" jdbcType="VARCHAR" />
    <result column="PrivateName" property="privateName" jdbcType="VARCHAR" />
    <result column="PrivateIp" property="privateIp" jdbcType="VARCHAR" />
    <result column="LastPingTime" property="lastPingTime" jdbcType="TIMESTAMP" />
    <result column="CommandId" property="commandId" jdbcType="INTEGER" />
    <result column="ServerStateId" property="serverStateId" jdbcType="INTEGER" />
    <result column="CommandTime" property="commandTime" jdbcType="TIMESTAMP" />
    <result column="StateChangeTime" property="stateChangeTime" jdbcType="TIMESTAMP" />
    <result column="WebHostName" property="webHostName" jdbcType="VARCHAR" />
    <result column="DateCreated" property="dateCreated" jdbcType="TIMESTAMP" />
    <result column="MachineType" property="machineType" jdbcType="VARCHAR" />
    <result column="Processors" property="processors" jdbcType="INTEGER" />
    <result column="OSVersion" property="OSVersion" jdbcType="VARCHAR" />
    <result column="WebServiceHost" property="webServiceHost" jdbcType="VARCHAR" />
    <result column="ProductVersion" property="productVersion" jdbcType="VARCHAR" />
    <result column="ManagementCredentialId" property="managementCredentialId" jdbcType="CHAR" />
    <result column="Modified" property="modified" jdbcType="TIMESTAMP" />
    <result column="Comments" property="comments" jdbcType="VARCHAR" />
    <result column="CompressorVersion" property="compressorVersion" jdbcType="VARCHAR" />
  </resultMap>
  <sql id="Example_Where_Clause" >
    <!--
      WARNING - @mbggenerated
      This element is automatically generated by MyBatis Generator, do not modify.
      This element was generated on Fri Feb 10 14:15:10 MST 2012.
    -->
    <where >
      <foreach collection="oredCriteria" item="criteria" separator="or" >
        <if test="criteria.valid" >
          <trim prefix="(" suffix=")" prefixOverrides="and" >
            <foreach collection="criteria.criteria" item="criterion" >
              <choose >
                <when test="criterion.noValue" >
                  and ${criterion.condition}
                </when>
                <when test="criterion.singleValue" >
                  and ${criterion.condition} #{criterion.value}
                </when>
                <when test="criterion.betweenValue" >
                  and ${criterion.condition} #{criterion.value} and #{criterion.secondValue}
                </when>
                <when test="criterion.listValue" >
                  and ${criterion.condition}
                  <foreach collection="criterion.value" item="listItem" open="(" close=")" separator="," >
                    #{listItem}
                  </foreach>
                </when>
              </choose>
            </foreach>
          </trim>
        </if>
      </foreach>
    </where>
  </sql>
  <sql id="Update_By_Example_Where_Clause" >
    <!--
      WARNING - @mbggenerated
      This element is automatically generated by MyBatis Generator, do not modify.
      This element was generated on Fri Feb 10 14:15:10 MST 2012.
    -->
    <where >
      <foreach collection="example.oredCriteria" item="criteria" separator="or" >
        <if test="criteria.valid" >
          <trim prefix="(" suffix=")" prefixOverrides="and" >
            <foreach collection="criteria.criteria" item="criterion" >
              <choose >
                <when test="criterion.noValue" >
                  and ${criterion.condition}
                </when>
                <when test="criterion.singleValue" >
                  and ${criterion.condition} #{criterion.value}
                </when>
                <when test="criterion.betweenValue" >
                  and ${criterion.condition} #{criterion.value} and #{criterion.secondValue}
                </when>
                <when test="criterion.listValue" >
                  and ${criterion.condition}
                  <foreach collection="criterion.value" item="listItem" open="(" close=")" separator="," >
                    #{listItem}
                  </foreach>
                </when>
              </choose>
            </foreach>
          </trim>
        </if>
      </foreach>
    </where>
  </sql>
  <sql id="Base_Column_List" >
    <!--
      WARNING - @mbggenerated
      This element is automatically generated by MyBatis Generator, do not modify.
      This element was generated on Fri Feb 10 14:15:10 MST 2012.
    -->
    ServerId, ImageId, InstanceId, PublicName, PublicIp, PrivateName, PrivateIp, LastPingTime, 
    CommandId, ServerStateId, CommandTime, StateChangeTime, WebHostName, DateCreated, 
    MachineType, Processors, OSVersion, WebServiceHost, ProductVersion, ManagementCredentialId, 
    Modified, Comments, CompressorVersion
  </sql>
  <select id="selectByExample" resultMap="BaseResultMap" parameterType="com.smedia.sqzserver.dataservice.model.base.ServersExample" >
    <!--
      WARNING - @mbggenerated
      This element is automatically generated by MyBatis Generator, do not modify.
      This element was generated on Fri Feb 10 14:15:10 MST 2012.
    -->
    select
    <if test="distinct" >
      distinct
    </if>
    <include refid="Base_Column_List" />
    from Servers
    <if test="_parameter != null" >
      <include refid="Example_Where_Clause" />
    </if>
    <if test="orderByClause != null" >
      order by ${orderByClause}
    </if>
  </select>
  <select id="selectByPrimaryKey" resultMap="BaseResultMap" parameterType="java.lang.String" >
    <!--
      WARNING - @mbggenerated
      This element is automatically generated by MyBatis Generator, do not modify.
      This element was generated on Fri Feb 10 14:15:10 MST 2012.
    -->
    select 
    <include refid="Base_Column_List" />
    from Servers
    where ServerId = #{serverId,jdbcType=CHAR}
  </select>
  <delete id="deleteByPrimaryKey" parameterType="java.lang.String" >
    <!--
      WARNING - @mbggenerated
      This element is automatically generated by MyBatis Generator, do not modify.
      This element was generated on Fri Feb 10 14:15:10 MST 2012.
    -->
    delete from Servers
    where ServerId = #{serverId,jdbcType=CHAR}
  </delete>
  <delete id="deleteByExample" parameterType="com.smedia.sqzserver.dataservice.model.base.ServersExample" >
    <!--
      WARNING - @mbggenerated
      This element is automatically generated by MyBatis Generator, do not modify.
      This element was generated on Fri Feb 10 14:15:10 MST 2012.
    -->
    delete from Servers
    <if test="_parameter != null" >
      <include refid="Example_Where_Clause" />
    </if>
  </delete>
  <insert id="insert" parameterType="com.smedia.sqzserver.dataservice.model.base.Servers" >
    <!--
      WARNING - @mbggenerated
      This element is automatically generated by MyBatis Generator, do not modify.
      This element was generated on Fri Feb 10 14:15:10 MST 2012.
    -->
    insert into Servers (ServerId, ImageId, InstanceId, 
      PublicName, PublicIp, PrivateName, 
      PrivateIp, LastPingTime, CommandId, 
      ServerStateId, CommandTime, StateChangeTime, 
      WebHostName, DateCreated, MachineType, 
      Processors, OSVersion, WebServiceHost, 
      ProductVersion, ManagementCredentialId, Modified, 
      Comments, CompressorVersion)
    values (#{serverId,jdbcType=CHAR}, #{imageId,jdbcType=VARCHAR}, #{instanceId,jdbcType=VARCHAR}, 
      #{publicName,jdbcType=VARCHAR}, #{publicIp,jdbcType=VARCHAR}, #{privateName,jdbcType=VARCHAR}, 
      #{privateIp,jdbcType=VARCHAR}, #{lastPingTime,jdbcType=TIMESTAMP}, #{commandId,jdbcType=INTEGER}, 
      #{serverStateId,jdbcType=INTEGER}, #{commandTime,jdbcType=TIMESTAMP}, #{stateChangeTime,jdbcType=TIMESTAMP}, 
      #{webHostName,jdbcType=VARCHAR}, #{dateCreated,jdbcType=TIMESTAMP}, #{machineType,jdbcType=VARCHAR}, 
      #{processors,jdbcType=INTEGER}, #{OSVersion,jdbcType=VARCHAR}, #{webServiceHost,jdbcType=VARCHAR}, 
      #{productVersion,jdbcType=VARCHAR}, #{managementCredentialId,jdbcType=CHAR}, #{modified,jdbcType=TIMESTAMP}, 
      #{comments,jdbcType=VARCHAR}, #{compressorVersion,jdbcType=VARCHAR})
  </insert>
  <insert id="insertSelective" parameterType="com.smedia.sqzserver.dataservice.model.base.Servers" >
    <!--
      WARNING - @mbggenerated
      This element is automatically generated by MyBatis Generator, do not modify.
      This element was generated on Fri Feb 10 14:15:10 MST 2012.
    -->
    insert into Servers
    <trim prefix="(" suffix=")" suffixOverrides="," >
      <if test="serverId != null" >
        ServerId,
      </if>
      <if test="imageId != null" >
        ImageId,
      </if>
      <if test="instanceId != null" >
        InstanceId,
      </if>
      <if test="publicName != null" >
        PublicName,
      </if>
      <if test="publicIp != null" >
        PublicIp,
      </if>
      <if test="privateName != null" >
        PrivateName,
      </if>
      <if test="privateIp != null" >
        PrivateIp,
      </if>
      <if test="lastPingTime != null" >
        LastPingTime,
      </if>
      <if test="commandId != null" >
        CommandId,
      </if>
      <if test="serverStateId != null" >
        ServerStateId,
      </if>
      <if test="commandTime != null" >
        CommandTime,
      </if>
      <if test="stateChangeTime != null" >
        StateChangeTime,
      </if>
      <if test="webHostName != null" >
        WebHostName,
      </if>
      <if test="dateCreated != null" >
        DateCreated,
      </if>
      <if test="machineType != null" >
        MachineType,
      </if>
      <if test="processors != null" >
        Processors,
      </if>
      <if test="OSVersion != null" >
        OSVersion,
      </if>
      <if test="webServiceHost != null" >
        WebServiceHost,
      </if>
      <if test="productVersion != null" >
        ProductVersion,
      </if>
      <if test="managementCredentialId != null" >
        ManagementCredentialId,
      </if>
      <if test="modified != null" >
        Modified,
      </if>
      <if test="comments != null" >
        Comments,
      </if>
      <if test="compressorVersion != null" >
        CompressorVersion,
      </if>
    </trim>
    <trim prefix="values (" suffix=")" suffixOverrides="," >
      <if test="serverId != null" >
        #{serverId,jdbcType=CHAR},
      </if>
      <if test="imageId != null" >
        #{imageId,jdbcType=VARCHAR},
      </if>
      <if test="instanceId != null" >
        #{instanceId,jdbcType=VARCHAR},
      </if>
      <if test="publicName != null" >
        #{publicName,jdbcType=VARCHAR},
      </if>
      <if test="publicIp != null" >
        #{publicIp,jdbcType=VARCHAR},
      </if>
      <if test="privateName != null" >
        #{privateName,jdbcType=VARCHAR},
      </if>
      <if test="privateIp != null" >
        #{privateIp,jdbcType=VARCHAR},
      </if>
      <if test="lastPingTime != null" >
        #{lastPingTime,jdbcType=TIMESTAMP},
      </if>
      <if test="commandId != null" >
        #{commandId,jdbcType=INTEGER},
      </if>
      <if test="serverStateId != null" >
        #{serverStateId,jdbcType=INTEGER},
      </if>
      <if test="commandTime != null" >
        #{commandTime,jdbcType=TIMESTAMP},
      </if>
      <if test="stateChangeTime != null" >
        #{stateChangeTime,jdbcType=TIMESTAMP},
      </if>
      <if test="webHostName != null" >
        #{webHostName,jdbcType=VARCHAR},
      </if>
      <if test="dateCreated != null" >
        #{dateCreated,jdbcType=TIMESTAMP},
      </if>
      <if test="machineType != null" >
        #{machineType,jdbcType=VARCHAR},
      </if>
      <if test="processors != null" >
        #{processors,jdbcType=INTEGER},
      </if>
      <if test="OSVersion != null" >
        #{OSVersion,jdbcType=VARCHAR},
      </if>
      <if test="webServiceHost != null" >
        #{webServiceHost,jdbcType=VARCHAR},
      </if>
      <if test="productVersion != null" >
        #{productVersion,jdbcType=VARCHAR},
      </if>
      <if test="managementCredentialId != null" >
        #{managementCredentialId,jdbcType=CHAR},
      </if>
      <if test="modified != null" >
        #{modified,jdbcType=TIMESTAMP},
      </if>
      <if test="comments != null" >
        #{comments,jdbcType=VARCHAR},
      </if>
      <if test="compressorVersion != null" >
        #{compressorVersion,jdbcType=VARCHAR},
      </if>
    </trim>
  </insert>
  <select id="countByExample" parameterType="com.smedia.sqzserver.dataservice.model.base.ServersExample" resultType="java.lang.Integer" >
    <!--
      WARNING - @mbggenerated
      This element is automatically generated by MyBatis Generator, do not modify.
      This element was generated on Fri Feb 10 14:15:10 MST 2012.
    -->
    select count(*) from Servers
    <if test="_parameter != null" >
      <include refid="Example_Where_Clause" />
    </if>
  </select>
  <update id="updateByExampleSelective" parameterType="map" >
    <!--
      WARNING - @mbggenerated
      This element is automatically generated by MyBatis Generator, do not modify.
      This element was generated on Fri Feb 10 14:15:10 MST 2012.
    -->
    update Servers
    <set >
      <if test="record.serverId != null" >
        ServerId = #{record.serverId,jdbcType=CHAR},
      </if>
      <if test="record.imageId != null" >
        ImageId = #{record.imageId,jdbcType=VARCHAR},
      </if>
      <if test="record.instanceId != null" >
        InstanceId = #{record.instanceId,jdbcType=VARCHAR},
      </if>
      <if test="record.publicName != null" >
        PublicName = #{record.publicName,jdbcType=VARCHAR},
      </if>
      <if test="record.publicIp != null" >
        PublicIp = #{record.publicIp,jdbcType=VARCHAR},
      </if>
      <if test="record.privateName != null" >
        PrivateName = #{record.privateName,jdbcType=VARCHAR},
      </if>
      <if test="record.privateIp != null" >
        PrivateIp = #{record.privateIp,jdbcType=VARCHAR},
      </if>
      <if test="record.lastPingTime != null" >
        LastPingTime = #{record.lastPingTime,jdbcType=TIMESTAMP},
      </if>
      <if test="record.commandId != null" >
        CommandId = #{record.commandId,jdbcType=INTEGER},
      </if>
      <if test="record.serverStateId != null" >
        ServerStateId = #{record.serverStateId,jdbcType=INTEGER},
      </if>
      <if test="record.commandTime != null" >
        CommandTime = #{record.commandTime,jdbcType=TIMESTAMP},
      </if>
      <if test="record.stateChangeTime != null" >
        StateChangeTime = #{record.stateChangeTime,jdbcType=TIMESTAMP},
      </if>
      <if test="record.webHostName != null" >
        WebHostName = #{record.webHostName,jdbcType=VARCHAR},
      </if>
      <if test="record.dateCreated != null" >
        DateCreated = #{record.dateCreated,jdbcType=TIMESTAMP},
      </if>
      <if test="record.machineType != null" >
        MachineType = #{record.machineType,jdbcType=VARCHAR},
      </if>
      <if test="record.processors != null" >
        Processors = #{record.processors,jdbcType=INTEGER},
      </if>
      <if test="record.OSVersion != null" >
        OSVersion = #{record.OSVersion,jdbcType=VARCHAR},
      </if>
      <if test="record.webServiceHost != null" >
        WebServiceHost = #{record.webServiceHost,jdbcType=VARCHAR},
      </if>
      <if test="record.productVersion != null" >
        ProductVersion = #{record.productVersion,jdbcType=VARCHAR},
      </if>
      <if test="record.managementCredentialId != null" >
        ManagementCredentialId = #{record.managementCredentialId,jdbcType=CHAR},
      </if>
      <if test="record.modified != null" >
        Modified = #{record.modified,jdbcType=TIMESTAMP},
      </if>
      <if test="record.comments != null" >
        Comments = #{record.comments,jdbcType=VARCHAR},
      </if>
      <if test="record.compressorVersion != null" >
        CompressorVersion = #{record.compressorVersion,jdbcType=VARCHAR},
      </if>
    </set>
    <if test="_parameter != null" >
      <include refid="Update_By_Example_Where_Clause" />
    </if>
  </update>
  <update id="updateByExample" parameterType="map" >
    <!--
      WARNING - @mbggenerated
      This element is automatically generated by MyBatis Generator, do not modify.
      This element was generated on Fri Feb 10 14:15:10 MST 2012.
    -->
    update Servers
    set ServerId = #{record.serverId,jdbcType=CHAR},
      ImageId = #{record.imageId,jdbcType=VARCHAR},
      InstanceId = #{record.instanceId,jdbcType=VARCHAR},
      PublicName = #{record.publicName,jdbcType=VARCHAR},
      PublicIp = #{record.publicIp,jdbcType=VARCHAR},
      PrivateName = #{record.privateName,jdbcType=VARCHAR},
      PrivateIp = #{record.privateIp,jdbcType=VARCHAR},
      LastPingTime = #{record.lastPingTime,jdbcType=TIMESTAMP},
      CommandId = #{record.commandId,jdbcType=INTEGER},
      ServerStateId = #{record.serverStateId,jdbcType=INTEGER},
      CommandTime = #{record.commandTime,jdbcType=TIMESTAMP},
      StateChangeTime = #{record.stateChangeTime,jdbcType=TIMESTAMP},
      WebHostName = #{record.webHostName,jdbcType=VARCHAR},
      DateCreated = #{record.dateCreated,jdbcType=TIMESTAMP},
      MachineType = #{record.machineType,jdbcType=VARCHAR},
      Processors = #{record.processors,jdbcType=INTEGER},
      OSVersion = #{record.OSVersion,jdbcType=VARCHAR},
      WebServiceHost = #{record.webServiceHost,jdbcType=VARCHAR},
      ProductVersion = #{record.productVersion,jdbcType=VARCHAR},
      ManagementCredentialId = #{record.managementCredentialId,jdbcType=CHAR},
      Modified = #{record.modified,jdbcType=TIMESTAMP},
      Comments = #{record.comments,jdbcType=VARCHAR},
      CompressorVersion = #{record.compressorVersion,jdbcType=VARCHAR}
    <if test="_parameter != null" >
      <include refid="Update_By_Example_Where_Clause" />
    </if>
  </update>
  <update id="updateByPrimaryKeySelective" parameterType="com.smedia.sqzserver.dataservice.model.base.Servers" >
    <!--
      WARNING - @mbggenerated
      This element is automatically generated by MyBatis Generator, do not modify.
      This element was generated on Fri Feb 10 14:15:10 MST 2012.
    -->
    update Servers
    <set >
      <if test="imageId != null" >
        ImageId = #{imageId,jdbcType=VARCHAR},
      </if>
      <if test="instanceId != null" >
        InstanceId = #{instanceId,jdbcType=VARCHAR},
      </if>
      <if test="publicName != null" >
        PublicName = #{publicName,jdbcType=VARCHAR},
      </if>
      <if test="publicIp != null" >
        PublicIp = #{publicIp,jdbcType=VARCHAR},
      </if>
      <if test="privateName != null" >
        PrivateName = #{privateName,jdbcType=VARCHAR},
      </if>
      <if test="privateIp != null" >
        PrivateIp = #{privateIp,jdbcType=VARCHAR},
      </if>
      <if test="lastPingTime != null" >
        LastPingTime = #{lastPingTime,jdbcType=TIMESTAMP},
      </if>
      <if test="commandId != null" >
        CommandId = #{commandId,jdbcType=INTEGER},
      </if>
      <if test="serverStateId != null" >
        ServerStateId = #{serverStateId,jdbcType=INTEGER},
      </if>
      <if test="commandTime != null" >
        CommandTime = #{commandTime,jdbcType=TIMESTAMP},
      </if>
      <if test="stateChangeTime != null" >
        StateChangeTime = #{stateChangeTime,jdbcType=TIMESTAMP},
      </if>
      <if test="webHostName != null" >
        WebHostName = #{webHostName,jdbcType=VARCHAR},
      </if>
      <if test="dateCreated != null" >
        DateCreated = #{dateCreated,jdbcType=TIMESTAMP},
      </if>
      <if test="machineType != null" >
        MachineType = #{machineType,jdbcType=VARCHAR},
      </if>
      <if test="processors != null" >
        Processors = #{processors,jdbcType=INTEGER},
      </if>
      <if test="OSVersion != null" >
        OSVersion = #{OSVersion,jdbcType=VARCHAR},
      </if>
      <if test="webServiceHost != null" >
        WebServiceHost = #{webServiceHost,jdbcType=VARCHAR},
      </if>
      <if test="productVersion != null" >
        ProductVersion = #{productVersion,jdbcType=VARCHAR},
      </if>
      <if test="managementCredentialId != null" >
        ManagementCredentialId = #{managementCredentialId,jdbcType=CHAR},
      </if>
      <if test="modified != null" >
        Modified = #{modified,jdbcType=TIMESTAMP},
      </if>
      <if test="comments != null" >
        Comments = #{comments,jdbcType=VARCHAR},
      </if>
      <if test="compressorVersion != null" >
        CompressorVersion = #{compressorVersion,jdbcType=VARCHAR},
      </if>
    </set>
    where ServerId = #{serverId,jdbcType=CHAR}
  </update>
  <update id="updateByPrimaryKey" parameterType="com.smedia.sqzserver.dataservice.model.base.Servers" >
    <!--
      WARNING - @mbggenerated
      This element is automatically generated by MyBatis Generator, do not modify.
      This element was generated on Fri Feb 10 14:15:10 MST 2012.
    -->
    update Servers
    set ImageId = #{imageId,jdbcType=VARCHAR},
      InstanceId = #{instanceId,jdbcType=VARCHAR},
      PublicName = #{publicName,jdbcType=VARCHAR},
      PublicIp = #{publicIp,jdbcType=VARCHAR},
      PrivateName = #{privateName,jdbcType=VARCHAR},
      PrivateIp = #{privateIp,jdbcType=VARCHAR},
      LastPingTime = #{lastPingTime,jdbcType=TIMESTAMP},
      CommandId = #{commandId,jdbcType=INTEGER},
      ServerStateId = #{serverStateId,jdbcType=INTEGER},
      CommandTime = #{commandTime,jdbcType=TIMESTAMP},
      StateChangeTime = #{stateChangeTime,jdbcType=TIMESTAMP},
      WebHostName = #{webHostName,jdbcType=VARCHAR},
      DateCreated = #{dateCreated,jdbcType=TIMESTAMP},
      MachineType = #{machineType,jdbcType=VARCHAR},
      Processors = #{processors,jdbcType=INTEGER},
      OSVersion = #{OSVersion,jdbcType=VARCHAR},
      WebServiceHost = #{webServiceHost,jdbcType=VARCHAR},
      ProductVersion = #{productVersion,jdbcType=VARCHAR},
      ManagementCredentialId = #{managementCredentialId,jdbcType=CHAR},
      Modified = #{modified,jdbcType=TIMESTAMP},
      Comments = #{comments,jdbcType=VARCHAR},
      CompressorVersion = #{compressorVersion,jdbcType=VARCHAR}
    where ServerId = #{serverId,jdbcType=CHAR}
  </update>
</mapper>